peak_autocorrect/__init__.py
peak_autocorrect/core.py
peak_autocorrect-0.1.4.dist-info/METADATA
peak_autocorrect-0.1.4.dist-info/WHEEL
peak_autocorrect-0.1.4.dist-info/top_level.txt
peak_autocorrect-0.1.4.dist-info/RECORD
